gpt_ghostwriter
