Metadata-Version: 2.1
Name: gpt-ghostwriter
Version: 1.0.3
Summary: Summarizes commit messages for you automagically.
Home-page: https://github.com/iMerica/gpt-ghostwriter
Author: Michael
Author-email: writemichaelmartinez@gmail.com
License: MIT
Project-URL: Documentation, https://pyscaffold.org/
Platform: any
Classifier: Development Status :: 4 - Beta
Classifier: Programming Language :: Python
Provides-Extra: testing
License-File: LICENSE.txt
